MkIOT/__init__.py
MkIOT/devices/__init__.py
MkIOT/devices/mesh.py
MkIOT/discovery/__init__.py
MkIOT/discovery/broadcast.py
MkIOT/discovery/fast.py
MkIOT/discovery/robust.py
MkIOT/imp/__init__.py
MkIOT/imp/broadcast.py
MkIOT/imp/iot_device.py
MkIOT/imp/iot_server.py
MkIOT/imp/messaging.py
MkIOT/prebuilds/__init__.py
MkIOT/prebuilds/network_camera/__init__.py
MkIOT/prebuilds/network_camera/camera.py
MkIOT/prebuilds/network_camera/screen.py
MkIOT/prebuilds/network_speaker/__init__.py
MkIOT/prebuilds/network_speaker/mic.py
MkIOT/prebuilds/network_speaker/speaker.py
MkIOT/tools/__init__.py
MkIOT/tools/audio.py
MkIOT/tools/image.py
MkIOT/tutorials/__init__.py
MkIOT/tutorials/lesson_1.py
MkIOT/tutorials/lesson_2.py
MkIOT/tutorials/lesson_3.py
MkIOT/tutorials/lesson_4.py
MkIOT/tutorials/lesson_5.py
MkIOT/verification/__init__.py
MkIOT-0.0.0.3.7.dist-info/LICENSE
MkIOT-0.0.0.3.7.dist-info/METADATA
MkIOT-0.0.0.3.7.dist-info/WHEEL
MkIOT-0.0.0.3.7.dist-info/top_level.txt
MkIOT-0.0.0.3.7.dist-info/RECORD
