Metadata-Version: 2.1
Name: MkIOT
Version: 0.0.0.3.7
Summary: MkNxGn IOT Services
Home-page: https://mknxgn.com/
Author: Mark Cartagena
Author-email: mark@mknxgn.com
License: UNKNOWN
Platform: UNKNOWN
Classifier: Programming Language :: Python :: 3
Classifier: License :: OSI Approved :: MIT License
Classifier: Operating System :: OS Independent
Requires-Dist: mknxgn-essentials (>=0.1.35.12)
